{
  "/_app": "pages/_app.js",
  "/api/products": "pages/api/products.js",
  "/_document": "pages/_document.js",
  "/_error": "pages/_error.js",
  "/about": "pages/about.html",
  "/bag": "pages/bag.html",
  "/productCard": "pages/productCard.html",
  "/contact": "pages/contact.html",
  "/productDetails": "pages/productDetails.html",
  "/createAccount": "pages/createAccount.html",
  "/productGrid": "pages/productGrid.html",
  "/": "pages/index.html",
  "/test-styles": "pages/test-styles.html",
  "/signIn": "pages/signIn.html",
  "/profile": "pages/profile.html",
  "/404": "pages/404.html"
}